schem/__init__.py
schem/__main__.py
schem/_version.py
schem/components.py
schem/elements.py
schem/exceptions.py
schem/grid.py
schem/level.py
schem/levels.py
schem/molecule.py
schem/precognition.py
schem/schem_random.py
schem/solution.py
schem/terrains.py
schem/waldo.py
schem-0.35.0.dist-info/licenses/LICENSE
schem-0.35.0.dist-info/METADATA
schem-0.35.0.dist-info/WHEEL
schem-0.35.0.dist-info/top_level.txt
schem-0.35.0.dist-info/RECORD
