Metadata-Version: 2.4
Name: schem
Version: 0.35.0
Summary: Clean Room implementation of the backend of SpaceChem (https://www.zachtronics.com/spacechem).
Home-page: https://github.com/spacechem-community-developers/SChem
Author: Zig
Author-email: junknenopok@gmail.com
Classifier: Programming Language :: Python :: 3
Classifier: License :: OSI Approved :: MIT License
Classifier: Operating System :: OS Independent
Requires-Python: >=3.7
License-File: LICENSE
Requires-Dist: clipboard>=0.0.4
Requires-Dist: numpy>=1.19.1
Requires-Dist: rich>=9.13.0
Requires-Dist: cursor>=1.3.4
Requires-Dist: scipy>=1.6.3
Dynamic: license-file
